hwcomponents_adc/__init__.py
hwcomponents_adc/_version.py
hwcomponents_adc/energy_correlation.csv
hwcomponents_adc/headers.py
hwcomponents_adc/main.py
hwcomponents_adc/model.py
hwcomponents_adc/murmannsurvey.py
hwcomponents_adc/optimizer.py
hwcomponents_adc/update_model.py
hwcomponents_adc/adc_data/adc_list.csv
hwcomponents_adc/adc_data/citation.bib
hwcomponents_adc/adc_data/model.yaml
hwcomponents_adc-1.0.16.dist-info/METADATA
hwcomponents_adc-1.0.16.dist-info/WHEEL
hwcomponents_adc-1.0.16.dist-info/top_level.txt
hwcomponents_adc-1.0.16.dist-info/RECORD
