Metadata-Version: 2.4
Name: hwcomponents-adc
Version: 1.0.16
Summary: A package for estimating the energy and area of Analog-Digital Converters
Author-email: Tanner Andrulis <Andrulis@mit.edu>
License-Expression: MIT
Keywords: accelerator,hardware,energy,estimation,analog,adc
Classifier: Development Status :: 3 - Alpha
Classifier: Programming Language :: Python :: 3
Classifier: Topic :: Scientific/Engineering :: Electronic Design Automation (EDA)
Requires-Python: >=3.12
Requires-Dist: hwcomponents
Requires-Dist: PyYAML
Requires-Dist: numpy
Requires-Dist: pandas
